crowd_api/__init__.py
crowd_api-0.1.0.dist-info/LICENSE.txt
crowd_api-0.1.0.dist-info/METADATA
crowd_api-0.1.0.dist-info/WHEEL
crowd_api-0.1.0.dist-info/top_level.txt
crowd_api-0.1.0.dist-info/RECORD
