Metadata-Version: 2.1
Name: crowd-api
Version: 0.1.0
Summary: Python library for Atlassian Crowd
Home-page: https://github.com/m4ce/crowd-api-python
Download-URL: https://github.com/m4ce/crowd-api-python/tarball/0.1.0
Author: Matteo Cerutti
Author-email: matteo.cerutti@hotmail.co.uk
Keywords: crowd
License-File: LICENSE.txt
Requires-Dist: requests
